{
  "meta": {
    "run_id": "abl_lr_ssf_0.001__vit_b__ssf__dtd__s42__f100__r8__a64__p20",
    "tag": "abl_lr_ssf_0.001",
    "method": "ssf",
    "dataset": "dtd",
    "backbone": "vit_b",
    "train_fraction": 1.0,
    "num_classes": 47,
    "epochs": 20,
    "batch_size": 128,
    "lr": 0.001,
    "seed": 42,
    "trainable_params": 109871,
    "total_params": 85908527,
    "pct_trainable": 0.1279,
    "best_acc": 80.053,
    "final_acc": 79.84,
    "peak_mem_mb": 8899.0,
    "train_time_s": 400.5,
    "time_per_epoch_s": 20.0,
    "throughput_img_s": 185.4,
    "model": "vit_base_patch16_224.augreg_in21k",
    "lora_r": 8,
    "adapter_dim": 64,
    "vpt_prompts": 20
  },
  "curve": [
    {
      "epoch": 1,
      "train_loss": 4.2376,
      "test_acc": 40.479,
      "epoch_time_s": 49.7
    },
    {
      "epoch": 2,
      "train_loss": 1.8686,
      "test_acc": 72.553,
      "epoch_time_s": 12.4
    },
    {
      "epoch": 4,
      "train_loss": 1.1017,
      "test_acc": 77.5,
      "epoch_time_s": 13.0
    },
    {
      "epoch": 6,
      "train_loss": 0.9433,
      "test_acc": 78.67,
      "epoch_time_s": 13.5
    },
    {
      "epoch": 8,
      "train_loss": 0.8695,
      "test_acc": 80.053,
      "epoch_time_s": 13.9
    },
    {
      "epoch": 10,
      "train_loss": 0.8293,
      "test_acc": 79.894,
      "epoch_time_s": 14.0
    },
    {
      "epoch": 12,
      "train_loss": 0.8032,
      "test_acc": 79.734,
      "epoch_time_s": 14.5
    },
    {
      "epoch": 14,
      "train_loss": 0.7899,
      "test_acc": 79.894,
      "epoch_time_s": 14.4
    },
    {
      "epoch": 16,
      "train_loss": 0.781,
      "test_acc": 80.053,
      "epoch_time_s": 14.1
    },
    {
      "epoch": 18,
      "train_loss": 0.7788,
      "test_acc": 79.84,
      "epoch_time_s": 14.5
    },
    {
      "epoch": 19,
      "train_loss": 0.7774,
      "test_acc": 79.787,
      "epoch_time_s": 14.4
    },
    {
      "epoch": 20,
      "train_loss": 0.7772,
      "test_acc": 79.84,
      "epoch_time_s": 14.2
    }
  ]
}